yooncloud_dart/__init__.py
yooncloud_dart/_utils.py
yooncloud_dart/dart.py
yooncloud_dart/dart_event.py
yooncloud_dart/dart_finstate.py
yooncloud_dart/dart_list.py
yooncloud_dart/dart_regstate.py
yooncloud_dart/dart_report.py
yooncloud_dart/dart_search.py
yooncloud_dart/dart_share.py
yooncloud_dart/dart_utils.py
yooncloud_dart/dart_xbrl.py
yooncloud_dart/dartfss_helper.py
yooncloud_dart/dartfss_utils.py
yooncloud_dart/search.py
yooncloud_dart/api/__init__.py
yooncloud_dart/api/dart_report.py
yooncloud_dart/api/dart_search.py
yooncloud_dart/api/finstate.py
yooncloud_dart/api/report.py
yooncloud_dart/api/search.py
yooncloud_dart/api/share.py
yooncloud_dart-0.0.4.dist-info/METADATA
yooncloud_dart-0.0.4.dist-info/WHEEL
yooncloud_dart-0.0.4.dist-info/top_level.txt
yooncloud_dart-0.0.4.dist-info/RECORD
