Metadata-Version: 2.1
Name: yooncloud-dart
Version: 0.0.4
Requires-Python: >=3.8
Requires-Dist: numpy ==1.26.4
Requires-Dist: pandas ==2.2.1
Requires-Dist: arelle-release
